cook/sidecar/__init__.py
cook/sidecar/__main__.py
cook/sidecar/config.py
cook/sidecar/exit_sentinel.py
cook/sidecar/file_server.py
cook/sidecar/progress.py
cook/sidecar/tracker.py
cook/sidecar/util.py
cook/sidecar/version.py
cook_sidecar-1.2.3.dist-info/METADATA
cook_sidecar-1.2.3.dist-info/WHEEL
cook_sidecar-1.2.3.dist-info/entry_points.txt
cook_sidecar-1.2.3.dist-info/top_level.txt
cook_sidecar-1.2.3.dist-info/RECORD
