Metadata-Version: 2.1
Name: cook-sidecar
Version: 1.2.3
Summary: Two Sigma's Cook Sidecar
Home-page: UNKNOWN
Author: UNKNOWN
Author-email: UNKNOWN
License: UNKNOWN
Platform: UNKNOWN
Requires-Dist: flask (~=1.1.0)
Requires-Dist: gunicorn (~=20.1.0)
Requires-Dist: requests (~=2.27.0)
